odoo/addons/base_import_security_group/README.rst
odoo/addons/base_import_security_group/__init__.py
odoo/addons/base_import_security_group/__manifest__.py
odoo/addons/base_import_security_group/demo/assets.xml
odoo/addons/base_import_security_group/i18n/base_import_security_group.pot
odoo/addons/base_import_security_group/i18n/ca.po
odoo/addons/base_import_security_group/i18n/de.po
odoo/addons/base_import_security_group/i18n/es.po
odoo/addons/base_import_security_group/i18n/fr.po
odoo/addons/base_import_security_group/i18n/gl.po
odoo/addons/base_import_security_group/i18n/hr.po
odoo/addons/base_import_security_group/i18n/it.po
odoo/addons/base_import_security_group/i18n/pt.po
odoo/addons/base_import_security_group/i18n/sk.po
odoo/addons/base_import_security_group/models/__init__.py
odoo/addons/base_import_security_group/models/models.py
odoo/addons/base_import_security_group/readme/CONTRIBUTORS.rst
odoo/addons/base_import_security_group/readme/DESCRIPTION.rst
odoo/addons/base_import_security_group/security/base_import_security_group_security.xml
odoo/addons/base_import_security_group/static/description/icon.png
odoo/addons/base_import_security_group/static/description/icon.svg
odoo/addons/base_import_security_group/static/description/index.html
odoo/addons/base_import_security_group/static/src/js/import.js
odoo/addons/base_import_security_group/static/src/js/tour_import.js
odoo/addons/base_import_security_group/tests/__init__.py
odoo/addons/base_import_security_group/tests/test_base_import_security_group.py
odoo/addons/base_import_security_group/views/base_import.xml
odoo13_addon_base_import_security_group-13.0.1.0.1.dev3.dist-info/METADATA
odoo13_addon_base_import_security_group-13.0.1.0.1.dev3.dist-info/WHEEL
odoo13_addon_base_import_security_group-13.0.1.0.1.dev3.dist-info/top_level.txt
odoo13_addon_base_import_security_group-13.0.1.0.1.dev3.dist-info/RECORD
