Metadata-Version: 2.1
Name: odoo13-addon-base-import-security-group
Version: 13.0.1.0.1.dev3
Summary: Group-based permissions for importing CSV files
Home-page: https://github.com/OCA/server-ux
Author: Odoo Community Association (OCA), Alejandro Santana <alejandrosantana@anubia.es>, Onestein
Author-email: support@odoo-community.org
License: AGPL-3
Platform: UNKNOWN
Classifier: Programming Language :: Python
Classifier: Framework :: Odoo
Classifier: Framework :: Odoo :: 13.0
Classifier: License :: OSI Approved :: GNU Affero General Public License v3
Requires-Python: >=3.5
Requires-Dist: odoo <13.1dev,>=13.0a
